{
  "path": "/Users/varadiimre/DEV/kb3/packages/backend/data/files/content_1759239138580_91b2c35d.html",
  "size": 17621,
  "createdAt": "2025-09-30T13:32:18.582Z",
  "updatedAt": "2025-09-30T13:32:18.582Z",
  "mimeType": "text/html",
  "checksum": "91b2c35d20b4cf3a6015a827d17aee67",
  "isCompressed": false,
  "isEncrypted": false,
  "metadata": {
    "url": "https://google.com",
    "mimeType": "text/html",
    "originalSize": 17621,
    "fetchedAt": "2025-09-30T13:32:18.580Z",
    "headers": {},
    "scraperUsed": "http"
  }
}