{
  "path": "/Users/varadiimre/DEV/kb3/packages/backend/data/files/content_1759238648470_d4291ca2.html",
  "size": 17616,
  "createdAt": "2025-09-30T13:24:08.472Z",
  "updatedAt": "2025-09-30T13:24:08.472Z",
  "mimeType": "text/html",
  "checksum": "d4291ca2c6dc6d07e85e7d427e9c32bf",
  "isCompressed": false,
  "isEncrypted": false,
  "metadata": {
    "url": "https://google.com",
    "mimeType": "text/html",
    "originalSize": 17616,
    "fetchedAt": "2025-09-30T13:24:08.470Z",
    "headers": {},
    "scraperUsed": "http"
  }
}