{
  "path": "/Users/varadiimre/DEV/kb3/packages/backend/data/files/oj_1759244843753_b6d6fde4.html",
  "size": 404033,
  "createdAt": "2025-09-30T15:07:23.754Z",
  "updatedAt": "2025-09-30T15:07:23.754Z",
  "mimeType": "text/html",
  "checksum": "b6d6fde4d11fb2deb659bb736893e39a",
  "isCompressed": false,
  "isEncrypted": false,
  "metadata": {
    "url": "https://eur-lex.europa.eu/eli/dir/1993/42/oj",
    "mimeType": "text/html",
    "originalSize": 404033,
    "fetchedAt": "2025-09-30T15:07:23.753Z",
    "headers": {},
    "scraperUsed": "http"
  }
}