{
  "path": "/Users/varadiimre/DEV/kb3/packages/backend/data/files/oj_1759244193801_032b9ab9.html",
  "size": 404033,
  "createdAt": "2025-09-30T14:56:33.801Z",
  "updatedAt": "2025-09-30T14:56:33.801Z",
  "mimeType": "text/html",
  "checksum": "032b9ab9aef0db75a6e7d6237a0ee6a7",
  "isCompressed": false,
  "isEncrypted": false,
  "metadata": {
    "url": "https://eur-lex.europa.eu/eli/dir/1993/42/oj",
    "mimeType": "text/html",
    "originalSize": 404033,
    "fetchedAt": "2025-09-30T14:56:33.801Z",
    "headers": {},
    "scraperUsed": "http"
  }
}